[
{"name": "Drag API (Part 1: Sortable)","keywords": ["Javascript","API","Drag"],"description": "everything about drag api.","created": "2020-04-14","modified": "2020-04-18","path":"/blog/drag-sortable"},
{"name": "让手机成为工作的助力","keywords": ["Phone","Notification","Work"],"description": "Make phone help your work","created": "2020-04-16","modified": "2020-04-16","path":"/blog/work-with-phone"},
{"name": "Payment Request API","keywords": ["PaymentRequest","Javascript","API"],"description": "use Payment Request API","created": "2020-04-08","modified": "2020-04-09","path":"/blog/paymentrequest"},
{"name": "CSS matrix3d 旋转3D物体（实践篇）","keywords": ["Javascript","3D"],"description": "use css matrix3d rotate object in 3d","created": "2020-04-06","modified": "2020-04-08","path":"/blog/matrix3d-2"},
{"name": "CSS matrix3d 旋转3D物体（原理篇）","keywords": ["CSS","3D"],"description": "use css matrix3d rotate object in 3d","created": "2020-04-06","modified": "2020-04-08","path":"/blog/matrix3d"},
{"name": "设计简洁的博客界面","keywords": ["Design","Blog","Concise"],"description": "Design a concise blog interface","created": "2020-04-05","modified": "2020-04-06","path":"/blog/concise-blog-interface"},
{"name": "Javascript 流式解析JSON数组","keywords": ["Stream","Javascript","JSON"],"description": "use stream api to read JSON Array","created": "2020-04-04","modified": "2020-04-05","path":"/blog/stream-json-array"},
{"name": "Arex0 Markdown Example","keywords": ["Markdown"],"description": "a Example to show markdown style.","created": "2020-04-03","modified": "2020-04-03","path":"/blog/example"}
]
